saruca_uuv/__init__.py
saruca_uuv/main.py
saruca_uuv/comprehend_system_layer/Classes/VehicleComprehendLayer.py
saruca_uuv/comprehend_system_layer/Methods/localization.py
saruca_uuv/comprehend_system_layer/Methods/state.py
saruca_uuv/control_system_layer/Classes/ControlLayer.py
saruca_uuv/control_system_layer/Methods/assignment.py
saruca_uuv/control_system_layer/Methods/behaviour.py
saruca_uuv/control_system_layer/Methods/command.py
saruca_uuv/control_system_layer/Methods/engineBreakdown.py
saruca_uuv/control_system_layer/Methods/orbit.py
saruca_uuv/sensing_system_layer/Classes/EntityLayer.py
saruca_uuv/sensing_system_layer/Methods/imageProcessing.py
saruca_uuv/sensing_system_layer/Methods/variables.py
saruca_uuv-0.1.7.dist-info/LICENSE
saruca_uuv-0.1.7.dist-info/METADATA
saruca_uuv-0.1.7.dist-info/WHEEL
saruca_uuv-0.1.7.dist-info/top_level.txt
saruca_uuv-0.1.7.dist-info/RECORD
