Metadata-Version: 2.1
Name: saruca-uuv
Version: 0.1.7
Summary: Autonomous and manual control methods for UUVs
Home-page: https://github.com/SARUCA-YazilimEkibi/saruca_uuv
Author: SEMIH SAHIN
Author-email: esemihsahin@hotmail.com
License: MIT
Keywords: UUV,AUV,UNDERWATER
Platform: UNKNOWN
Classifier: Development Status :: 3 - Alpha
Classifier: Intended Audience :: Developers
Classifier: Topic :: Software Development :: Build Tools
Classifier: License :: OSI Approved :: MIT License
Classifier: Programming Language :: Python :: 3
Classifier: Programming Language :: Python :: 3.4
Classifier: Programming Language :: Python :: 3.5
Classifier: Programming Language :: Python :: 3.6
Requires-Python: >=3.6
License-File: LICENSE
Requires-Dist: opencv-python
Requires-Dist: numpy
